graiax/shortcut/__init__.py
graiax/shortcut/_typing_util.py
graiax/shortcut/_util.py
graiax/shortcut/formatter.py
graiax/shortcut/interrupt.py
graiax/shortcut/saya.py
graiax/shortcut/text_parser.py
graiax/shortcut/commander/__init__.py
graiax/shortcut/commander/_util.py
graiax/shortcut/commander/creart.py
graiax/shortcut/commander/saya.py
graiax_shortcut-0.3.0.dist-info/LICENSE
graiax_shortcut-0.3.0.dist-info/METADATA
graiax_shortcut-0.3.0.dist-info/WHEEL
graiax_shortcut-0.3.0.dist-info/top_level.txt
graiax_shortcut-0.3.0.dist-info/RECORD
