Metadata-Version: 2.1
Name: graiax-shortcut
Version: 0.3.0
Summary: Utilities for Graia Framework Community.
Author-email: BlueGlassBlock <blueglassblock@outlook.com>, RF-Tar-Railt <rf_tar_railt@qq.com>
License: MIT
Project-URL: Repository, https://github.com/GraiaCommunity/Shortcut
Requires-Python: <4.0,>=3.8
License-File: LICENSE
Requires-Dist: graia-broadcast (<1.0.0,>=0.18)
Requires-Dist: creart (~=0.2)
Requires-Dist: graia-amnesia (~=0.7.0)
Requires-Dist: graia-scheduler (>=0.0.8)
Requires-Dist: graia-saya (<0.1.0,>=0.0.17)
Requires-Dist: typing-extensions (>=4.4.0)
Requires-Dist: pydantic (~=1.8)
